pvm/__init__.py
pypvm-0.0.1.dist-info/LICENSE
pypvm-0.0.1.dist-info/METADATA
pypvm-0.0.1.dist-info/WHEEL
pypvm-0.0.1.dist-info/top_level.txt
pypvm-0.0.1.dist-info/RECORD
