Metadata-Version: 2.1
Name: pypvm
Version: 0.0.1
Summary: Implementation of the JAM PVM
Author-email: JAMdot Technologies <devops@jamdot.tech>
License: Apache License
Project-URL: Homepage, https://github.com/JAMdotTech/py-pvm
Classifier: Programming Language :: Python :: 3
Classifier: License :: OSI Approved :: Apache Software License
Classifier: Operating System :: OS Independent
Requires-Python: >=3.8
License-File: LICENSE
Requires-Dist: setuptools~=69.0.3
Provides-Extra: dev
Requires-Dist: coverage==5.3; extra == "dev"
Requires-Dist: pytest>=6.1.2; extra == "dev"
